vtt2text/__init__.py
vtt2text-0.1.2.dist-info/LICENSE
vtt2text-0.1.2.dist-info/METADATA
vtt2text-0.1.2.dist-info/WHEEL
vtt2text-0.1.2.dist-info/top_level.txt
vtt2text-0.1.2.dist-info/RECORD
