Metadata-Version: 2.1
Name: vtt2text
Version: 0.1.2
Summary: A small package to clean up the content of a subtitle file to text
Home-page: https://github.com/vuanhtuan1012/vtt2text
Author: VU Anh Tuan
Author-email: vuanhtuan1012@outlook.com
License: UNKNOWN
Platform: UNKNOWN
Classifier: Programming Language :: Python :: 2.7
Classifier: Programming Language :: Python :: 3
Classifier: License :: OSI Approved :: MIT License
Classifier: Operating System :: OS Independent
Requires-Python: >=2.7
